{
    "name": "tutos",
    "version": "0.0.0",
    "description": "",
    "dependencies": {
        "core": "*",
        "radio": "*",
        "microphone": "*"
    },
    "files": [
        "README.md",
        "main.blocks",
        "main.ts",
        "tuto_1.md",
        "tuto_2.md",
        "tuto_3.md",
        "tuto_4.md",
        "tuto_5.md",
        "bonus_1.md",
        "bonus_2.md",
        "bonus_3.md",
        "bonus_4.md",
        "bonus_5.md"
    ],
    "testFiles": [
        "test.ts"
    ],
    "public": true,
    "targetVersions": {
        "target": "6.0.25",
        "targetId": "microbit"
    },
    "supportedTargets": [
        "microbit"
    ],
    "preferredEditor": "tsprj"
}
